fastapi_auth_keycloak/__init__.py
fastapi_auth_keycloak/api_user.py
fastapi_auth_keycloak/auth_credentials.py
fastapi_auth_keycloak/auth_header.py
fastapi_auth_keycloak/authorization.py
fastapi_auth_keycloak/backend.py
fastapi_auth_keycloak/client_access.py
fastapi_auth_keycloak/jwt/__init__.py
fastapi_auth_keycloak/jwt/backend.py
fastapi_auth_keycloak/jwt/user.py
fastapi_auth_keycloak/permissions.py
fastapi_auth_keycloak/public_key.py
fastapi_auth_keycloak/resource_access.py
fastapi_auth_keycloak/resource_permission.py
fastapi_auth_keycloak/ticket_request.py
fastapi_auth_keycloak/uma/__init__.py
fastapi_auth_keycloak/uma/authorize.py
fastapi_auth_keycloak/uma/exceptions.py
fastapi_auth_keycloak/uma/proto.py
fastapi_auth_keycloak/uma_authorize.py
fastapi_auth_keycloak/user.py
fastapi_auth_keycloak-0.9.0.dist-info/METADATA
fastapi_auth_keycloak-0.9.0.dist-info/WHEEL
fastapi_auth_keycloak-0.9.0.dist-info/RECORD
