Metadata-Version: 2.3
Name: fastapi-auth-keycloak
Version: 0.9.0
Summary: Keycloak authentication backend for FastAPI
License: MIT
Keywords: fastapi,keycloak,authentication,backend
Author: Dave Sutherland
Author-email: dave@daveography.ca
Requires-Python: >=3.9
Classifier: License :: OSI Approved :: MIT License
Classifier: Programming Language :: Python :: 3
Classifier: Programming Language :: Python :: 3.10
Classifier: Programming Language :: Python :: 3.11
Classifier: Programming Language :: Python :: 3.12
Classifier: Programming Language :: Python :: 3.13
Requires-Dist: fastapi (>=0.115.2,<1.0)
Requires-Dist: jwcrypto (>=1.5.6)
Requires-Dist: pydantic[email] (>=2.10.0)
Requires-Dist: python-keycloak (>=4.7.3)
Project-URL: Repository, https://github.com/Daveography/fastapi-auth-keycloak
